[
  {
    "key": "Customer",
    "data": {
      "id": 1,
      "name": "sushant patil",
      "age": 35,
      "country": "Sweden",
      "city": "Helsinborg"
    }
  },
  {
    "key": "Customer",
    "data": {
      "id": 2,
      "name": "Mark",
      "age": 39,
      "country": "Sweden",
      "city": "Malmo"
    }
  },
  {
    "key": "Customer",
    "data": {
      "id": 3,
      "name": "Henning Hamre",
      "age": 42,
      "country": "Norway",
      "profile": "Business Analyst"
    }
  },
  {
    "key": "Customer",
    "data": {
      "id": 4,
      "name": "Arpan Ray",
      "age": 38,
      "country": "Sweden",
      "profile": "Software Developer"
    }
  },
  {
    "key": "Customer",
    "data": {
      "id": 5,
      "name": "Jeremy",
      "age": 36,
      "country": "Sweden",
      "profile": "Lund"
    }
  }
]
